adaptkeybert/__init__.py
adaptkeybert/_attention.py
adaptkeybert/_highlight.py
adaptkeybert/_maxsum.py
adaptkeybert/_mmr.py
adaptkeybert/_model.py
adaptkeybert/backend/__init__.py
adaptkeybert/backend/_base.py
adaptkeybert/backend/_flair.py
adaptkeybert/backend/_gensim.py
adaptkeybert/backend/_hftransformers.py
adaptkeybert/backend/_sentencetransformers.py
adaptkeybert/backend/_spacy.py
adaptkeybert/backend/_use.py
adaptkeybert/backend/_utils.py
adaptkeybert-0.0.2.dist-info/LICENSE
adaptkeybert-0.0.2.dist-info/METADATA
adaptkeybert-0.0.2.dist-info/WHEEL
adaptkeybert-0.0.2.dist-info/top_level.txt
adaptkeybert-0.0.2.dist-info/RECORD
