Metadata-Version: 2.1
Name: adaptkeybert
Version: 0.0.2
Summary: AdaptKeyBERT extended keyphrase extraction with zero-shot and few-shot semi-supervised domain adaptation.
Home-page: https://github.com/AmanPriyanshu/AdaptKeyBERT
Author: Aman Priyanshu
Author-email: amanpriyanshusms2001@gmail.com
Keywords: nlp bert keyword extraction embeddings zeroshot fewshot semisupervised
Classifier: Programming Language :: Python
Classifier: Intended Audience :: Science/Research
Classifier: Intended Audience :: Developers
Classifier: Topic :: Scientific/Engineering :: Artificial Intelligence
Classifier: License :: OSI Approved :: MIT License
Classifier: Topic :: Scientific/Engineering
Classifier: Operating System :: Microsoft :: Windows
Classifier: Operating System :: POSIX
Classifier: Operating System :: Unix
Classifier: Operating System :: MacOS
Classifier: Programming Language :: Python :: 3.7
Classifier: Programming Language :: Python :: 3.6
Classifier: Programming Language :: Python :: 3.8
Requires-Python: >=3.6
License-File: LICENSE
Requires-Dist: sentence-transformers (>=0.3.8)
Requires-Dist: scikit-learn (>=0.22.2)
Requires-Dist: numpy (>=1.18.5)
Requires-Dist: rich (>=10.4.0)
Provides-Extra: dev
Requires-Dist: mkdocs (>=1.1) ; extra == 'dev'
Requires-Dist: mkdocs-material (>=4.6.3) ; extra == 'dev'
Requires-Dist: mkdocstrings (>=0.8.0) ; extra == 'dev'
Requires-Dist: pytest (>=5.4.3) ; extra == 'dev'
Requires-Dist: pytest-cov (>=2.6.1) ; extra == 'dev'
Requires-Dist: flake8 (>=3.6.0) ; extra == 'dev'
Requires-Dist: pre-commit (>=2.2.0) ; extra == 'dev'
Requires-Dist: black (>=19.3b0) ; extra == 'dev'
Provides-Extra: docs
Requires-Dist: mkdocs (>=1.1) ; extra == 'docs'
Requires-Dist: mkdocs-material (>=4.6.3) ; extra == 'docs'
Requires-Dist: mkdocstrings (>=0.8.0) ; extra == 'docs'
Provides-Extra: flair
Requires-Dist: transformers (>=3.5.1) ; extra == 'flair'
Requires-Dist: torch (>=1.4.0) ; extra == 'flair'
Requires-Dist: flair (>=0.7) ; extra == 'flair'
Provides-Extra: gensim
Requires-Dist: gensim (>=3.6.0) ; extra == 'gensim'
Provides-Extra: spacy
Requires-Dist: spacy (>=3.0.1) ; extra == 'spacy'
Provides-Extra: test
Requires-Dist: pytest (>=5.4.3) ; extra == 'test'
Requires-Dist: pytest-cov (>=2.6.1) ; extra == 'test'
Requires-Dist: flake8 (>=3.6.0) ; extra == 'test'
Requires-Dist: pre-commit (>=2.2.0) ; extra == 'test'
Requires-Dist: black (>=19.3b0) ; extra == 'test'
Provides-Extra: use
Requires-Dist: tensorflow ; extra == 'use'
Requires-Dist: tensorflow-hub ; extra == 'use'
Requires-Dist: tensorflow-text ; extra == 'use'
